quick_cache.py
quick_cache-0.3.1.dist-info/METADATA
quick_cache-0.3.1.dist-info/RECORD
quick_cache-0.3.1.dist-info/WHEEL
quick_cache-0.3.1.dist-info/entry_points.txt
quick_cache-0.3.1.dist-info/top_level.txt
