Metadata-Version: 2.1
Name: quick-cache
Version: 0.3.1
Summary: QuickCache is a quick to use and easy to set up cache implementation.
Home-page: https://github.com/JosuaKrause/quick_cache
Author: Josua Krause
Author-email: josua.krause@gmail.com
License: MIT
Keywords: cache quick easy
Platform: UNKNOWN
Classifier: Development Status :: 4 - Beta
Classifier: License :: OSI Approved :: MIT License
Classifier: Programming Language :: Python :: 2
Classifier: Programming Language :: Python :: 2.6
Classifier: Programming Language :: Python :: 2.7
Classifier: Programming Language :: Python :: 3
Classifier: Programming Language :: Python :: 3.6
Provides-Extra: test
Provides-Extra: dev
Provides-Extra: dev
Provides-Extra: test
